{"329050 Storeb\u00f8lgen Lund": {"A1": ["A", "", ""], "A2": ["A", "", ""], "A3": ["A", "", ""], "A4": ["A", "", ""], "A6": ["A", "", ""], "AG1": ["A", "", ""], "AP1": ["A", "", ""], "AS": ["AS", "Avspasering", ""], "BPU": ["B", "Barn/Passer syk u/11 dager", ""], "D": ["D", "", ""], "D2": ["D", "", ""], "D3": ["D", "", ""], "D5": ["D", "", ""], "D6": ["D", "", ""], "DT": ["U", "", ""], "EM": ["EM", "Egenmelding", ""], "EMK": ["S", "XXX (fra 5/8): Egenmelding Kronisk Syk (vedtak NAV)", ""], "EV": ["EV", "Ekstravakt", ""], "F1": ["F", "", ""], "F2": ["F", "", ""], "F3": ["F", "", ""], "F4": ["F", "", ""], "FA": ["FK", "Forskj\u00f8vet arbeidstid", ""], "FE": ["FE", "Ferie", ""], "FK": ["FK", "Forskj\u00f8vet arbeidstid - kort varsel", ""], "FP1": ["U", "Foreldrepermisjon 100% (vedtak NAV)", ""], "FP8": ["U", "Foreldrepermisjon 80% (vedtak NAV)", ""], "FU": ["O", "Frav\u00e6r 2", ""], "FV": ["O", "Frav\u00e6r Vakant Stilling", ""], "GM": ["A", "", ""], "HV": ["U", "Hjemmevakt", ""], "IB": ["IB", "Internt bytte av vakt", ""], "KFE": ["S", "xxxKorona frav\u00e6r Egenmeldt - avvikskode 1110", ""], "KFK": ["S", "xxxKorona frav\u00e6r Karantene - avvikskode 1110", ""], "KFS": ["S", "xxxKorona frav\u00e6r Sykmeldt UNDER 17 dager - avvikskode 1997", ""], "KI": ["S", "xxxKorona  vikar ekstra/sykdom/karantene  - LTA 397. Konto 102000", ""], "KO": ["A", "", ""], "KO2": ["A", "xxxKorona OVERTID 200% (over 35,5 t/uka / 100% st.) - LTA 395", ""], "M": ["A", "", ""], "N": ["N", "", ""], "NE": ["A", "", ""], "NHH": ["A", "", ""], "OLV": ["OLV", "Oppl\u00e6ringsvakt", ""], "OT": ["OT", "Overtid", ""], "PK": ["U", "Permisjon Kurs", ""], "PM": ["P", "Permisjon Med L\u00f8nn", ""], "PS": ["P", "Permisjon, l\u00f8nn STOPPET med personalmelding", ""], "PT": ["U", "Permisjon", ""], "PTV": ["P", "Permisjon TV og VO Arbeid", ""], "PV": ["P", "Permisjon Velferd", ""], "SMG": ["B", "XXX (fra 5/8):Sykmelding pga graviditet (vedtak NAV)", ""], "SO": ["S", "Sykmelding OVER 16 dager", ""], "SP": ["U", "Svangerskapspenger (vedtak NAV - HUSK kopi av s\u00f8knad til l\u00f8nsavd.)", ""], "SU": ["S", "Sykmelding UNDER  17 dager", ""], "U1": ["A", "", ""], "U2": ["A", "", ""], "U3": ["A", "", ""], "UH": ["A", "Utrykning ved hjemmevakt", ""], "VA": ["U", "Vikar Avspasering", ""], "VB": ["U", "xxxVAKTBANK vakt HUSK timer til Timebank", ""], "VF": ["U", "Vikar Ferie", ""], "VK": ["U", "Vikar Kurs", ""], "VM": ["U", "M\u00f8te / Vikar M\u00f8te", ""], "VP": ["U", "Vikar Permisjon", ""], "VS": ["U", "Vikar Sykdom Kort", ""], "VSL": ["U", "Vikar Sykdom Lang", ""], "VSV": ["U", "Vikar Svangerskap", ""], "VTV": ["U", "Vikar/arb. Tillitsvalgt/Verneombud", ""], "VV": ["U", "Vikar Vakant stilling", ""], "nan": ["U", "", ""]}, "346058 Sykepleier Legevakt": {"A": ["A", "", ""], "A-": ["A", "", ""], "A0": ["A", "", ""], "AAP": ["U", "AAP(vedtak NAV), l\u00f8nn STOPPET med personalmelding", ""], "AS": ["AS", "Avspasering", ""], "AT": ["A", "", ""], "AT0": ["A", "", ""], "AU": ["A", "", ""], "BPO": ["B", "Barn/Passer syk o/10 dager", ""], "BPU": ["B", "Barn/Passer syk u/11 dager", ""], "D": ["D", "", ""], "D-": ["A", "", ""], "D0": ["D", "", ""], "D3": ["D", "", ""], "DK": ["U", "", ""], "DK1": ["A", "", ""], "DK2": ["A", "", ""], "DK3": ["A", "", ""], "DT": ["U", "", ""], "EL7": ["A", "", ""], "EM": ["EM", "Egenmelding", ""], "EV": ["EV", "Ekstravakt", ""], "F1": ["F", "", ""], "F2": ["F", "", ""], "F3": ["F", "", ""], "FA": ["FK", "Forskj\u00f8vet arbeidstid", ""], "FE": ["FE", "Ferie", ""], "FK": ["FK", "Forskj\u00f8vet arbeidstid - kort varsel", ""], "FL": ["O", "Frav\u00e6r 1", ""], "FP1": ["U", "Foreldrepermisjon 100% (vedtak NAV)", ""], "FU": ["O", "Frav\u00e6r 2", ""], "H3": ["F", "", ""], "IB": ["IB", "Internt bytte av vakt", ""], "IU": ["A", "", ""], "KFE": ["S", "xxxKorona frav\u00e6r Egenmeldt - avvikskode 1110", ""], "KFK": ["S", "xxxKorona frav\u00e6r Karantene - avvikskode 1110", ""], "KFS": ["S", "xxxKorona frav\u00e6r Sykmeldt UNDER 17 dager - avvikskode 1997", ""], "KI": ["S", "xxxKorona  vikar ekstra/sykdom/karantene  - LTA 397. Konto 102000", ""], "KO2": ["A", "xxxKorona OVERTID 200% (over 35,5 t/uka / 100% st.) - LTA 395", ""], "KO3": ["A", "xxxKorona OVERTID 300% (Helligdag) (fra 35,5 t/uka / 100% st.) - LTA 396", ""], "M": ["A", "", ""], "M0": ["A", "", ""], "M01": ["A", "", ""], "M1": ["A", "", ""], "M1-": ["A", "", ""], "MA": ["A", "", ""], "MN": ["A", "", ""], "MS": ["A", "", ""], "N": ["N", "", ""], "N-": ["A", "", ""], "N0": ["A", "", ""], "N03": ["A", "", ""], "N1": ["N", "", ""], "N3": ["N", "", ""], "N3-": ["A", "", ""], "OLV": ["OLV", "Oppl\u00e6ringsvakt", ""], "OT": ["OT", "Overtid", ""], "OU": ["U", "Opptjening av fri", ""], "P": ["U", "", ""], "PA": ["U", "", ""], "PK": ["U", "Permisjon Kurs", ""], "PM": ["P", "Permisjon Med L\u00f8nn", ""], "PR": ["A", "", ""], "PRH": ["A", "", ""], "PS": ["P", "Permisjon, l\u00f8nn STOPPET med personalmelding", ""], "PT": ["U", "Permisjon", ""], "PTV": ["P", "Permisjon TV og VO Arbeid", ""], "PV": ["P", "Permisjon Velferd", ""], "Q4": ["A", "", ""], "SA": ["U", "", ""], "SD": ["U", "", ""], "SF": ["F", "Seniorfri", ""], "SMG": ["B", "XXX (fra 5/8):Sykmelding pga graviditet (vedtak NAV)", ""], "SO": ["S", "Sykmelding OVER 16 dager", ""], "SU": ["S", "Sykmelding UNDER  17 dager", ""], "VA": ["U", "Vikar Avspasering", ""], "VF": ["U", "Vikar Ferie", ""], "VK": ["U", "Vikar Kurs", ""], "VP": ["U", "Vikar Permisjon", ""], "VS": ["U", "Vikar Sykdom Kort", ""], "VSL": ["U", "Vikar Sykdom Lang", ""], "VSV": ["U", "Vikar Svangerskap", ""], "VTV": ["U", "Vikar/arb. Tillitsvalgt/Verneombud", ""], "VV": ["U", "Vikar Vakant stilling", ""], "nan": ["U", "", ""]}, "351023 Tangvall avd. 2": {"A": ["A", "", ""], "A1": ["A", "", ""], "A2": ["A", "", ""], "A3": ["A", "", ""], "A4": ["A", "", ""], "AAP": ["U", "AAP(vedtak NAV), l\u00f8nn STOPPET med personalmelding", ""], "AS": ["AS", "Avspasering", ""], "AT": ["A", "", ""], "BPU": ["B", "Barn/Passer syk u/11 dager", ""], "D": ["D", "", ""], "D1": ["D", "", ""], "D2": ["D", "", ""], "D3": ["D", "", ""], "D4": ["D", "", ""], "D6": ["D", "", ""], "DK": ["U", "", ""], "DK1": ["A", "", ""], "DL": ["U", "", ""], "DL1": ["A", "", ""], "DOB": ["A", "", ""], "DT": ["U", "", ""], "EM": ["EM", "Egenmelding", ""], "EV": ["EV", "Ekstravakt", ""], "F1": ["F", "", ""], "F2": ["F", "", ""], "F3": ["F", "", ""], "F4": ["F", "", ""], "F5": ["F", "", ""], "FA": ["FK", "Forskj\u00f8vet arbeidstid", ""], "FE": ["FE", "Ferie", ""], "FK": ["FK", "Forskj\u00f8vet arbeidstid - kort varsel", ""], "FL": ["O", "Frav\u00e6r 1", ""], "FP1": ["U", "Foreldrepermisjon 100% (vedtak NAV)", ""], "FP8": ["U", "Foreldrepermisjon 80% (vedtak NAV)", ""], "FU": ["O", "Frav\u00e6r 2", ""], "FV": ["O", "Frav\u00e6r Vakant Stilling", ""], "H3": ["F", "", ""], "IB": ["IB", "Internt bytte av vakt", ""], "KFE": ["S", "xxxKorona frav\u00e6r Egenmeldt - avvikskode 1110", ""], "KFK": ["S", "xxxKorona frav\u00e6r Karantene - avvikskode 1110", ""], "KFS": ["S", "xxxKorona frav\u00e6r Sykmeldt UNDER 17 dager - avvikskode 1997", ""], "KI": ["S", "xxxKorona  vikar ekstra/sykdom/karantene  - LTA 397. Konto 102000", ""], "KO2": ["A", "xxxKorona OVERTID 200% (over 35,5 t/uka / 100% st.) - LTA 395", ""], "KO3": ["A", "xxxKorona OVERTID 300% (Helligdag) (fra 35,5 t/uka / 100% st.) - LTA 396", ""], "OA": ["X", "Overf\u00f8rt TIL annen avd", ""], "OF": ["U", "Overf\u00f8rt FRA annen avdeling", ""], "OLV": ["OLV", "Oppl\u00e6ringsvakt", ""], "OT": ["OT", "Overtid", ""], "OU": ["U", "Opptjening av fri", ""], "PK": ["U", "Permisjon Kurs", ""], "PKT": ["U", "xxxKorona vikar pensjonist timel\u00f8nn(LTA 399. KOnto 102000)", ""], "PM": ["P", "Permisjon Med L\u00f8nn", ""], "PS": ["P", "Permisjon, l\u00f8nn STOPPET med personalmelding", ""], "PTV": ["P", "Permisjon TV og VO Arbeid", ""], "PV": ["P", "Permisjon Velferd", ""], "REN": ["U", "", ""], "SO": ["S", "Sykmelding OVER 16 dager", ""], "SU": ["S", "Sykmelding UNDER  17 dager", ""], "TA": ["U", "", ""], "TA2": ["A", "", ""], "TAS": ["A", "", ""], "TD1": ["A", "", ""], "TD6": ["A", "", ""], "TDK": ["A", "", ""], "TK1": ["A", "", ""], "VA": ["U", "Vikar Avspasering", ""], "VAF": ["U", "Vikar Avsp F3", ""], "VF": ["U", "Vikar Ferie", ""], "VK": ["U", "Vikar Kurs", ""], "VM": ["U", "M\u00f8te / Vikar M\u00f8te", ""], "VP": ["U", "Vikar Permisjon", ""], "VS": ["U", "Vikar Sykdom Kort", ""], "VSL": ["U", "Vikar Sykdom Lang", ""], "VSV": ["U", "Vikar Svangerskap", ""], "VTV": ["U", "Vikar/arb. Tillitsvalgt/Verneombud", ""], "VV": ["U", "Vikar Vakant stilling", ""], "nan": ["U", "", ""]}, "351067 Ternevik omsorgsbolig": {"AS": ["AS", "Avspasering", ""], "BFU": ["U", "", ""], "BKU": ["A", "xxxKorona Barn/Passer syk u/11 dager - avvikskode 190", ""], "BPO": ["B", "Barn/Passer syk o/10 dager", ""], "BPU": ["B", "Barn/Passer syk u/11 dager", ""], "D": ["D", "", ""], "D1": ["D", "", ""], "D10": ["D", "", ""], "D11": ["D", "", ""], "D12": ["D", "", ""], "D2": ["D", "", ""], "D3": ["D", "", ""], "D4": ["D", "", ""], "D5": ["D", "", ""], "D7": ["D", "", ""], "D8": ["D", "", ""], "DD": ["U", "", ""], "EM": ["EM", "Egenmelding", ""], "EMK": ["S", "XXX (fra 5/8): Egenmelding Kronisk Syk (vedtak NAV)", ""], "EV": ["EV", "Ekstravakt", ""], "F1": ["F", "", ""], "F2": ["F", "", ""], "F3": ["F", "", ""], "F5": ["F", "", ""], "FA": ["FK", "Forskj\u00f8vet arbeidstid", ""], "FE": ["FE", "Ferie", ""], "FK": ["FK", "Forskj\u00f8vet arbeidstid - kort varsel", ""], "FL": ["O", "Frav\u00e6r 1", ""], "FU": ["O", "Frav\u00e6r 2", ""], "FV": ["O", "Frav\u00e6r Vakant Stilling", ""], "H3": ["F", "", ""], "H5": ["U", "", ""], "HF": ["U", "", ""], "IB": ["IB", "Internt bytte av vakt", ""], "K1": ["U", "", ""], "K2": ["U", "", ""], "K3": ["U", "", ""], "K4": ["U", "", ""], "K6": ["A", "", ""], "KFE": ["S", "xxxKorona frav\u00e6r Egenmeldt - avvikskode 1110", ""], "KFK": ["S", "xxxKorona frav\u00e6r Karantene - avvikskode 1110", ""], "KFS": ["S", "xxxKorona frav\u00e6r Sykmeldt UNDER 17 dager - avvikskode 1997", ""], "KI": ["S", "xxxKorona  vikar ekstra/sykdom/karantene  - LTA 397. Konto 102000", ""], "KO2": ["A", "xxxKorona OVERTID 200% (over 35,5 t/uka / 100% st.) - LTA 395", ""], "KO3": ["A", "xxxKorona OVERTID 300% (Helligdag) (fra 35,5 t/uka / 100% st.) - LTA 396", ""], "KSL": ["U", "XXX (fra 5/8):Sykmelding Kronisk (vedtak NAV)", ""], "OLV": ["OLV", "Oppl\u00e6ringsvakt", ""], "OML": ["A", "xxxOmsorgsperm Med l\u00f8nn", ""], "OT": ["OT", "Overtid", ""], "OU": ["U", "Opptjening av fri", ""], "PA": ["U", "Pensjonist avl\u00f8nning", ""], "PK": ["U", "Permisjon Kurs", ""], "PKT": ["U", "xxxKorona vikar pensjonist timel\u00f8nn(LTA 399. KOnto 102000)", ""], "PM": ["P", "Permisjon Med L\u00f8nn", ""], "PS": ["P", "Permisjon, l\u00f8nn STOPPET med personalmelding", ""], "PTV": ["P", "Permisjon TV og VO Arbeid", ""], "PV": ["P", "Permisjon Velferd", ""], "Q6": ["A", "", ""], "Q7H": ["A", "", ""], "SO": ["S", "Sykmelding OVER 16 dager", ""], "SU": ["S", "Sykmelding UNDER  17 dager", ""], "TK": ["U", "", ""], "VA": ["U", "Vikar Avspasering", ""], "VAF": ["U", "Vikar Avsp F3", ""], "VF": ["U", "Vikar Ferie", ""], "VK": ["U", "Vikar Kurs", ""], "VM": ["U", "M\u00f8te / Vikar M\u00f8te", ""], "VP": ["U", "Vikar Permisjon", ""], "VS": ["U", "Vikar Sykdom Kort", ""], "VSL": ["U", "Vikar Sykdom Lang", ""], "VSV": ["U", "Vikar Svangerskap", ""], "VTV": ["U", "Vikar/arb. Tillitsvalgt/Verneombud", ""], "VV": ["U", "Vikar Vakant stilling", ""], "nan": ["U", "", ""]}, "351068 x Ternevik omsorgsbolig natt": {"AAP": ["U", "AAP(vedtak NAV), l\u00f8nn STOPPET med personalmelding", ""], "AS": ["AS", "Avspasering", ""], "B\u00d8": ["A", "", ""], "EM": ["EM", "Egenmelding", ""], "EV": ["EV", "Ekstravakt", ""], "F1": ["F", "", ""], "F2": ["F", "", ""], "F3": ["F", "", ""], "FAP": ["U", "AAP korttidsfrav\u00e6r (sykdom og annet)", ""], "FE": ["FE", "Ferie", ""], "FU": ["O", "Frav\u00e6r 2", ""], "H3N": ["F", "", ""], "HF": ["U", "", ""], "KFE": ["S", "xxxKorona frav\u00e6r Egenmeldt - avvikskode 1110", ""], "KI": ["S", "xxxKorona  vikar ekstra/sykdom/karantene  - LTA 397. Konto 102000", ""], "KO2": ["A", "xxxKorona OVERTID 200% (over 35,5 t/uka / 100% st.) - LTA 395", ""], "M\u00d8": ["A", "", ""], "N": ["N", "", ""], "N1": ["N", "", ""], "NH": ["A", "", ""], "NH3": ["A", "", ""], "NM\u00d8": ["A", "", ""], "OA": ["X", "Overf\u00f8rt TIL annen avd", ""], "OLV": ["OLV", "Oppl\u00e6ringsvakt", ""], "OT": ["OT", "Overtid", ""], "PK": ["U", "Permisjon Kurs", ""], "Q7": ["A", "", ""], "SO": ["S", "Sykmelding OVER 16 dager", ""], "SU": ["S", "Sykmelding UNDER  17 dager", ""], "VF": ["U", "Vikar Ferie", ""], "VP": ["U", "Vikar Permisjon", ""], "VS": ["U", "Vikar Sykdom Kort", ""], "VSL": ["U", "Vikar Sykdom Lang", ""], "VV": ["U", "Vikar Vakant stilling", ""], "nan": ["U", "", ""]}, "352020 x Songdalstunet": {"A": ["A", "", ""], "A9": ["A", "", ""], "D": ["D", "", ""], "D1": ["D", "", ""], "D19": ["A", "", ""], "D20": ["A", "", ""], "D21": ["A", "", ""], "EV": ["EV", "Ekstravakt", ""], "F1": ["F", "", ""], "F2": ["F", "", ""], "F3": ["F", "", ""], "FE": ["FE", "Ferie", ""], "H3": ["F", "", ""], "H3N": ["F", "", ""], "KFK": ["S", "xxxKorona frav\u00e6r Karantene - avvikskode 1110", ""], "KFS": ["S", "xxxKorona frav\u00e6r Sykmeldt UNDER 17 dager - avvikskode 1997", ""], "KI": ["S", "xxxKorona  vikar ekstra/sykdom/karantene  - LTA 397. Konto 102000", ""], "N": ["N", "", ""], "OLV": ["OLV", "Oppl\u00e6ringsvakt", ""], "PKT": ["U", "xxxKorona vikar pensjonist timel\u00f8nn(LTA 399. KOnto 102000)", ""], "R1": ["A", "", ""], "R2": ["A", "", ""], "R3": ["A", "", ""], "R4": ["A", "", ""], "R5": ["A", "", ""], "VSL": ["U", "Vikar Sykdom Lang", ""], "nan": ["U", "", ""]}, "352027  Songdalstunet omsorgsbolig": {"A": ["A", "", ""], "A11": ["A", "", ""], "A7": ["A", "", ""], "A9": ["A", "", ""], "AAP": ["U", "AAP(vedtak NAV), l\u00f8nn STOPPET med personalmelding", ""], "AS": ["AS", "Avspasering", ""], "BKU": ["A", "xxxKorona Barn/Passer syk u/11 dager - avvikskode 190", ""], "BPU": ["B", "Barn/Passer syk u/11 dager", ""], "D": ["D", "", ""], "D0": ["D", "", ""], "D1": ["D", "", ""], "D11": ["D", "", ""], "D12": ["D", "", ""], "D2": ["D", "", ""], "D3": ["D", "", ""], "D9": ["D", "", ""], "DC": ["A", "", ""], "EM": ["EM", "Egenmelding", ""], "EMK": ["S", "XXX (fra 5/8): Egenmelding Kronisk Syk (vedtak NAV)", ""], "EV": ["EV", "Ekstravakt", ""], "F1": ["F", "", ""], "F2": ["F", "", ""], "F3": ["F", "", ""], "FA": ["FK", "Forskj\u00f8vet arbeidstid", ""], "FE": ["FE", "Ferie", ""], "FK": ["FK", "Forskj\u00f8vet arbeidstid - kort varsel", ""], "H3": ["F", "", ""], "H3N": ["F", "", ""], "IB": ["IB", "Internt bytte av vakt", ""], "K1": ["U", "", ""], "K2": ["U", "", ""], "KFE": ["S", "xxxKorona frav\u00e6r Egenmeldt - avvikskode 1110", ""], "KFK": ["S", "xxxKorona frav\u00e6r Karantene - avvikskode 1110", ""], "KFS": ["S", "xxxKorona frav\u00e6r Sykmeldt UNDER 17 dager - avvikskode 1997", ""], "KI": ["S", "xxxKorona  vikar ekstra/sykdom/karantene  - LTA 397. Konto 102000", ""], "N": ["N", "", ""], "OLV": ["OLV", "Oppl\u00e6ringsvakt", ""], "OT": ["OT", "Overtid", ""], "PKT": ["U", "xxxKorona vikar pensjonist timel\u00f8nn(LTA 399. KOnto 102000)", ""], "PM": ["P", "Permisjon Med L\u00f8nn", ""], "PS": ["P", "Permisjon, l\u00f8nn STOPPET med personalmelding", ""], "PT": ["U", "Permisjon", ""], "PV": ["P", "Permisjon Velferd", ""], "SO": ["S", "Sykmelding OVER 16 dager", ""], "SU": ["S", "Sykmelding UNDER  17 dager", ""], "VA": ["U", "Vikar Avspasering", ""], "VAF": ["U", "Vikar Avsp F3", ""], "VF": ["U", "Vikar Ferie", ""], "VK": ["U", "Vikar Kurs", ""], "VM": ["U", "M\u00f8te / Vikar M\u00f8te", ""], "VP": ["U", "Vikar Permisjon", ""], "VS": ["U", "Vikar Sykdom Kort", ""], "VSL": ["U", "Vikar Sykdom Lang", ""], "VSV": ["U", "Vikar Svangerskap", ""], "VV": ["U", "Vikar Vakant stilling", ""], "nan": ["U", "", ""]}, "352028  Songdalstunet Omsorgsbolig natt": {"A": ["A", "", ""], "A11": ["A", "", ""], "AS": ["AS", "Avspasering", ""], "AX": ["U", "", ""], "D": ["D", "", ""], "EM": ["EM", "Egenmelding", ""], "EV": ["EV", "Ekstravakt", ""], "F1": ["F", "", ""], "F2": ["F", "", ""], "F3": ["F", "", ""], "FE": ["FE", "Ferie", ""], "IB": ["IB", "Internt bytte av vakt", ""], "KFE": ["S", "xxxKorona frav\u00e6r Egenmeldt - avvikskode 1110", ""], "KFK": ["S", "xxxKorona frav\u00e6r Karantene - avvikskode 1110", ""], "KI": ["S", "xxxKorona  vikar ekstra/sykdom/karantene  - LTA 397. Konto 102000", ""], "N": ["N", "", ""], "OF": ["U", "Overf\u00f8rt FRA annen avdeling", ""], "OLV": ["OLV", "Oppl\u00e6ringsvakt", ""], "PK": ["U", "Permisjon Kurs", ""], "PTV": ["P", "Permisjon TV og VO Arbeid", ""], "SO": ["S", "Sykmelding OVER 16 dager", ""], "SU": ["S", "Sykmelding UNDER  17 dager", ""], "VA": ["U", "Vikar Avspasering", ""], "VF": ["U", "Vikar Ferie", ""], "VK": ["U", "Vikar Kurs", ""], "VM": ["U", "M\u00f8te / Vikar M\u00f8te", ""], "VP": ["U", "Vikar Permisjon", ""], "VS": ["U", "Vikar Sykdom Kort", ""], "VSL": ["U", "Vikar Sykdom Lang", ""], "VV": ["U", "Vikar Vakant stilling", ""], "nan": ["U", "", ""]}, "353047 Grimtunet omsorgsbolig": {"A": ["A", "", ""], "AK": ["A", "", ""], "AL": ["U", "", ""], "AS": ["AS", "Avspasering", ""], "AT": ["A", "", ""], "ATT": ["U", "", ""], "BPU": ["B", "Barn/Passer syk u/11 dager", ""], "D": ["D", "", ""], "DH": ["A", "", ""], "DK": ["U", "", ""], "DL": ["U", "", ""], "DS": ["U", "", ""], "DSS": ["A", "", ""], "DT": ["U", "", ""], "DX": ["A", "", ""], "DXX": ["A", "", ""], "EM": ["EM", "Egenmelding", ""], "EMK": ["S", "XXX (fra 5/8): Egenmelding Kronisk Syk (vedtak NAV)", ""], "EV": ["EV", "Ekstravakt", ""], "F1": ["F", "", ""], "F2": ["F", "", ""], "F3": ["F", "", ""], "FA": ["FK", "Forskj\u00f8vet arbeidstid", ""], "FE": ["FE", "Ferie", ""], "FK": ["FK", "Forskj\u00f8vet arbeidstid - kort varsel", ""], "FKO": ["A", "", ""], "FL": ["O", "Frav\u00e6r 1", ""], "FP1": ["U", "Foreldrepermisjon 100% (vedtak NAV)", ""], "FU": ["O", "Frav\u00e6r 2", ""], "FV": ["O", "Frav\u00e6r Vakant Stilling", ""], "H3": ["F", "", ""], "HH": ["X", "", ""], "IB": ["IB", "Internt bytte av vakt", ""], "KFE": ["S", "xxxKorona frav\u00e6r Egenmeldt - avvikskode 1110", ""], "KFK": ["S", "xxxKorona frav\u00e6r Karantene - avvikskode 1110", ""], "KFS": ["S", "xxxKorona frav\u00e6r Sykmeldt UNDER 17 dager - avvikskode 1997", ""], "KI": ["S", "xxxKorona  vikar ekstra/sykdom/karantene  - LTA 397. Konto 102000", ""], "KO2": ["A", "xxxKorona OVERTID 200% (over 35,5 t/uka / 100% st.) - LTA 395", ""], "KO3": ["A", "xxxKorona OVERTID 300% (Helligdag) (fra 35,5 t/uka / 100% st.) - LTA 396", ""], "KSL": ["U", "XXX (fra 5/8):Sykmelding Kronisk (vedtak NAV)", ""], "KTK": ["A", "", ""], "LS": ["A", "", ""], "LT": ["A", "", ""], "L\u00c6D": ["A", "", ""], "NS": ["U", "", ""], "OA": ["X", "Overf\u00f8rt TIL annen avd", ""], "OLV": ["OLV", "Oppl\u00e6ringsvakt", ""], "OPA": ["A", "", ""], "OPD": ["A", "", ""], "OT": ["OT", "Overtid", ""], "OU": ["U", "Opptjening av fri", ""], "PA": ["U", "Pensjonist avl\u00f8nning", ""], "PF": ["U", "xxxPermisjon Foreldre Svangerskap", ""], "PH": ["A", "", ""], "PK": ["U", "Permisjon Kurs", ""], "PKT": ["U", "xxxKorona vikar pensjonist timel\u00f8nn(LTA 399. KOnto 102000)", ""], "PM": ["P", "Permisjon Med L\u00f8nn", ""], "PRH": ["A", "", ""], "PS": ["P", "Permisjon, l\u00f8nn STOPPET med personalmelding", ""], "PT": ["U", "Permisjon", ""], "PV": ["P", "Permisjon Velferd", ""], "SF": ["F", "Seniorfri", ""], "SK": ["U", "", ""], "SO": ["S", "Sykmelding OVER 16 dager", ""], "STD": ["A", "", ""], "SU": ["S", "Sykmelding UNDER  17 dager", ""], "UND": ["U", "", ""], "UT2": ["U", "", ""], "UT3": ["A", "", ""], "UT4": ["U", "", ""], "UT5": ["U", "", ""], "UT6": ["A", "", ""], "UT7": ["A", "", ""], "UTA": ["A", "", ""], "VA": ["U", "Vikar Avspasering", ""], "VF": ["U", "Vikar Ferie", ""], "VK": ["U", "Vikar Kurs", ""], "VP": ["U", "Vikar Permisjon", ""], "VS": ["U", "Vikar Sykdom Kort", ""], "VSL": ["U", "Vikar Sykdom Lang", ""], "VV": ["U", "Vikar Vakant stilling", ""], "nan": ["U", "", ""]}, "353048 x Grimtunet omsorgsbolig natt": {"EM": ["EM", "Egenmelding", ""], "EV": ["EV", "Ekstravakt", ""], "F1": ["F", "", ""], "F2": ["F", "", ""], "F3": ["F", "", ""], "FE": ["FE", "Ferie", ""], "FU": ["O", "Frav\u00e6r 2", ""], "IB": ["IB", "Internt bytte av vakt", ""], "NM": ["U", "", ""], "NS": ["U", "", ""], "NSM": ["U", "", ""], "OT": ["OT", "Overtid", ""], "SU": ["S", "Sykmelding UNDER  17 dager", ""], "UND": ["U", "", ""], "UT2": ["U", "", ""], "UT5": ["U", "", ""], "VV": ["U", "Vikar Vakant stilling", ""], "nan": ["U", "", ""]}, "355021 Presteheia natt": {"AF1": ["U", "", ""], "AS": ["AS", "Avspasering", ""], "BPO": ["B", "Barn/Passer syk o/10 dager", ""], "BPU": ["B", "Barn/Passer syk u/11 dager", ""], "EM": ["EM", "Egenmelding", ""], "EMK": ["S", "XXX (fra 5/8): Egenmelding Kronisk Syk (vedtak NAV)", ""], "EV": ["EV", "Ekstravakt", ""], "F1": ["F", "", ""], "F2": ["F", "", ""], "F3": ["F", "", ""], "F5": ["F", "", ""], "FAG": ["X", "", ""], "FE": ["FE", "Ferie", ""], "FU": ["O", "Frav\u00e6r 2", ""], "FV": ["O", "Frav\u00e6r Vakant Stilling", ""], "HS1": ["A", "", ""], "IB": ["IB", "Internt bytte av vakt", ""], "KFE": ["S", "xxxKorona frav\u00e6r Egenmeldt - avvikskode 1110", ""], "KFK": ["S", "xxxKorona frav\u00e6r Karantene - avvikskode 1110", ""], "KFS": ["S", "xxxKorona frav\u00e6r Sykmeldt UNDER 17 dager - avvikskode 1997", ""], "KI": ["S", "xxxKorona  vikar ekstra/sykdom/karantene  - LTA 397. Konto 102000", ""], "KO2": ["A", "xxxKorona OVERTID 200% (over 35,5 t/uka / 100% st.) - LTA 395", ""], "KSL": ["U", "XXX (fra 5/8):Sykmelding Kronisk (vedtak NAV)", ""], "N": ["N", "", ""], "NF": ["U", "", ""], "NT": ["A", "", ""], "NU4": ["A", "", ""], "NU5": ["A", "", ""], "NU6": ["A", "", ""], "OLV": ["OLV", "Oppl\u00e6ringsvakt", ""], "OS": ["A", "", ""], "OS1": ["A", "", ""], "OT": ["OT", "Overtid", ""], "OT1": ["A", "", ""], "OTN": ["A", "", ""], "OU": ["U", "Opptjening av fri", ""], "PK": ["U", "Permisjon Kurs", ""], "PS": ["P", "Permisjon, l\u00f8nn STOPPET med personalmelding", ""], "PT": ["U", "Permisjon", ""], "PV": ["P", "Permisjon Velferd", ""], "SO": ["S", "Sykmelding OVER 16 dager", ""], "SU": ["S", "Sykmelding UNDER  17 dager", ""], "VA": ["U", "Vikar Avspasering", ""], "VF": ["U", "Vikar Ferie", ""], "VK": ["U", "Vikar Kurs", ""], "VM": ["U", "M\u00f8te / Vikar M\u00f8te", ""], "VP": ["U", "Vikar Permisjon", ""], "VS": ["U", "Vikar Sykdom Kort", ""], "VSL": ["U", "Vikar Sykdom Lang", ""], "VSV": ["U", "Vikar Svangerskap", ""], "VV": ["U", "Vikar Vakant stilling", ""], "nan": ["U", "", ""]}, "355027 X Presteheia omsorgsbolig": {"AS": ["AS", "Avspasering", ""], "BPU": ["B", "Barn/Passer syk u/11 dager", ""], "CE3": ["A", "", ""], "CGS": ["A", "", ""], "CGT": ["A", "", ""], "CS2": ["A", "", ""], "CS3": ["A", "", ""], "CS5": ["A", "", ""], "CS9": ["A", "", ""], "CT": ["A", "", ""], "CT3": ["A", "", ""], "CT5": ["A", "", ""], "D11": ["D", "", ""], "D18": ["A", "", ""], "D25": ["A", "", ""], "D3": ["D", "", ""], "DK": ["U", "", ""], "EM": ["EM", "Egenmelding", ""], "EMK": ["S", "XXX (fra 5/8): Egenmelding Kronisk Syk (vedtak NAV)", ""], "EV": ["EV", "Ekstravakt", ""], "F1": ["F", "", ""], "F2": ["F", "", ""], "F3": ["F", "", ""], "FA": ["FK", "Forskj\u00f8vet arbeidstid", ""], "FE": ["FE", "Ferie", ""], "FK": ["FK", "Forskj\u00f8vet arbeidstid - kort varsel", ""], "FK1": ["FK", "Fedrekvote 100% (vedtak NAV)", ""], "FK8": ["U", "Fedrekvote 80% (vedtak NAV)", ""], "FL": ["O", "Frav\u00e6r 1", ""], "FP1": ["U", "Foreldrepermisjon 100% (vedtak NAV)", ""], "FP8": ["U", "Foreldrepermisjon 80% (vedtak NAV)", ""], "FU": ["O", "Frav\u00e6r 2", ""], "FV": ["O", "Frav\u00e6r Vakant Stilling", ""], "HU1": ["A", "", ""], "HU3": ["A", "", ""], "IB": ["IB", "Internt bytte av vakt", ""], "KFE": ["S", "xxxKorona frav\u00e6r Egenmeldt - avvikskode 1110", ""], "KFK": ["S", "xxxKorona frav\u00e6r Karantene - avvikskode 1110", ""], "KI": ["S", "xxxKorona  vikar ekstra/sykdom/karantene  - LTA 397. Konto 102000", ""], "KO2": ["A", "xxxKorona OVERTID 200% (over 35,5 t/uka / 100% st.) - LTA 395", ""], "KSL": ["U", "XXX (fra 5/8):Sykmelding Kronisk (vedtak NAV)", ""], "M\u00d8": ["A", "", ""], "NS": ["U", "", ""], "OLV": ["OLV", "Oppl\u00e6ringsvakt", ""], "OT": ["OT", "Overtid", ""], "OU": ["U", "Opptjening av fri", ""], "PA": ["U", "Pensjonist avl\u00f8nning", ""], "PF": ["U", "xxxPermisjon Foreldre Svangerskap", ""], "PK": ["U", "Permisjon Kurs", ""], "PKT": ["U", "xxxKorona vikar pensjonist timel\u00f8nn(LTA 399. KOnto 102000)", ""], "PT": ["U", "Permisjon", ""], "PTV": ["P", "Permisjon TV og VO Arbeid", ""], "PV": ["P", "Permisjon Velferd", ""], "S": ["U", "", ""], "S1": ["U", "", ""], "S1M": ["U", "", ""], "S2H": ["A", "", ""], "SF": ["F", "Seniorfri", ""], "SH": ["U", "", ""], "SH1": ["U", "", ""], "SHK": ["U", "", ""], "SHM": ["U", "", ""], "SHU": ["U", "", ""], "SM": ["U", "", ""], "SMG": ["B", "XXX (fra 5/8):Sykmelding pga graviditet (vedtak NAV)", ""], "SO": ["S", "Sykmelding OVER 16 dager", ""], "SP": ["U", "Svangerskapspenger (vedtak NAV - HUSK kopi av s\u00f8knad til l\u00f8nsavd.)", ""], "SU": ["S", "Sykmelding UNDER  17 dager", ""], "SU1": ["U", "", ""], "SU2": ["A", "", ""], "SUH": ["U", "", ""], "T": ["U", "", ""], "T1": ["U", "", ""], "T1M": ["U", "", ""], "T1U": ["U", "", ""], "T2": ["U", "", ""], "T2M": ["U", "", ""], "T2U": ["U", "", ""], "T3": ["U", "", ""], "T3U": ["U", "", ""], "T5": ["U", "", ""], "T6": ["U", "", ""], "T9": ["A", "", ""], "TA": ["U", "", ""], "TAM": ["U", "", ""], "TH": ["U", "", ""], "TH1": ["U", "", ""], "TH3": ["A", "", ""], "THK": ["U", "", ""], "THM": ["U", "", ""], "THU": ["U", "", ""], "TK": ["U", "", ""], "TK2": ["U", "", ""], "TK5": ["U", "", ""], "TKD": ["A", "", ""], "TKM": ["A", "", ""], "TM": ["U", "", ""], "TP": ["U", "", ""], "TP1": ["A", "", ""], "V": ["A", "", ""], "VA": ["U", "Vikar Avspasering", ""], "VF": ["U", "Vikar Ferie", ""], "VK": ["U", "Vikar Kurs", ""], "VM": ["U", "M\u00f8te / Vikar M\u00f8te", ""], "VP": ["U", "Vikar Permisjon", ""], "VS": ["U", "Vikar Sykdom Kort", ""], "VSL": ["U", "Vikar Sykdom Lang", ""], "VSV": ["U", "Vikar Svangerskap", ""], "VTV": ["U", "Vikar/arb. Tillitsvalgt/Verneombud", ""], "VV": ["U", "Vikar Vakant stilling", ""], "nan": ["U", "", ""]}, "355028 x Presteheia omsorgsbolig natt": {"AS": ["AS", "Avspasering", ""], "BPO": ["B", "Barn/Passer syk o/10 dager", ""], "EM": ["EM", "Egenmelding", ""], "F1": ["F", "", ""], "F2": ["F", "", ""], "F3": ["F", "", ""], "FE": ["FE", "Ferie", ""], "IB": ["IB", "Internt bytte av vakt", ""], "KFE": ["S", "xxxKorona frav\u00e6r Egenmeldt - avvikskode 1110", ""], "KI": ["S", "xxxKorona  vikar ekstra/sykdom/karantene  - LTA 397. Konto 102000", ""], "N": ["N", "", ""], "NU4": ["A", "", ""], "NU5": ["A", "", ""], "OML": ["A", "xxxOmsorgsperm Med l\u00f8nn", ""], "OT": ["OT", "Overtid", ""], "OU": ["U", "Opptjening av fri", ""], "SO": ["S", "Sykmelding OVER 16 dager", ""], "SU": ["S", "Sykmelding UNDER  17 dager", ""], "VF": ["U", "Vikar Ferie", ""], "VK": ["U", "Vikar Kurs", ""], "VM": ["U", "M\u00f8te / Vikar M\u00f8te", ""], "VS": ["U", "Vikar Sykdom Kort", ""], "VSL": ["U", "Vikar Sykdom Lang", ""], "VV": ["U", "Vikar Vakant stilling", ""]}, "357022 Str\u00f8mme avd. 1": {"A": ["A", "", ""], "A1": ["A", "", ""], "A13": ["A", "", ""], "A2": ["A", "", ""], "A3": ["A", "", ""], "A4": ["A", "", ""], "A8": ["A", "", ""], "AM1": ["U", "", ""], "AM2": ["A", "", ""], "AM3": ["A", "", ""], "AS": ["AS", "Avspasering", ""], "BD": ["U", "", ""], "BD1": ["U", "", ""], "BD3": ["U", "", ""], "BD5": ["U", "", ""], "BD7": ["U", "", ""], "BPU": ["B", "Barn/Passer syk u/11 dager", ""], "D": ["D", "", ""], "D0": ["D", "", ""], "D1": ["D", "", ""], "D10": ["D", "", ""], "D11": ["D", "", ""], "D12": ["D", "", ""], "D14": ["D", "", ""], "D2": ["D", "", ""], "D3": ["D", "", ""], "D5": ["D", "", ""], "DM": ["U", "", ""], "DM0": ["A", "", ""], "DM3": ["A", "", ""], "EM": ["EM", "Egenmelding", ""], "EMG": ["A", "XXX (fra 5/8):Egenmelding pga Graviditet (vedtak NAV)", ""], "EV": ["EV", "Ekstravakt", ""], "F": ["F", "", ""], "F1": ["F", "", ""], "F2": ["F", "", ""], "F3": ["F", "", ""], "FA": ["FK", "Forskj\u00f8vet arbeidstid", ""], "FAG": ["X", "", ""], "FE": ["FE", "Ferie", ""], "FK": ["FK", "Forskj\u00f8vet arbeidstid - kort varsel", ""], "FL": ["O", "Frav\u00e6r 1", ""], "FU": ["O", "Frav\u00e6r 2", ""], "FV": ["O", "Frav\u00e6r Vakant Stilling", ""], "IB": ["IB", "Internt bytte av vakt", ""], "KFE": ["S", "xxxKorona frav\u00e6r Egenmeldt - avvikskode 1110", ""], "KFK": ["S", "xxxKorona frav\u00e6r Karantene - avvikskode 1110", ""], "KI": ["S", "xxxKorona  vikar ekstra/sykdom/karantene  - LTA 397. Konto 102000", ""], "M\u00d8": ["A", "", ""], "N": ["N", "", ""], "N1": ["N", "", ""], "N2": ["N", "", ""], "OA": ["X", "Overf\u00f8rt TIL annen avd", ""], "OLV": ["OLV", "Oppl\u00e6ringsvakt", ""], "OT": ["OT", "Overtid", ""], "PF": ["U", "xxxPermisjon Foreldre Svangerskap", ""], "PM": ["P", "", ""], "PS": ["P", "Permisjon, l\u00f8nn STOPPET med personalmelding", ""], "QD": ["U", "", ""], "SF": ["F", "Seniorfri", ""], "SO": ["S", "Sykmelding OVER 16 dager", ""], "SU": ["S", "Sykmelding UNDER  17 dager", ""], "T1": ["U", "", ""], "T2": ["U", "", ""], "VA": ["U", "Vikar Avspasering", ""], "VF": ["U", "Vikar Ferie", ""], "VK": ["U", "Vikar Kurs", ""], "VP": ["U", "Vikar Permisjon", ""], "VS": ["U", "Vikar Sykdom Kort", ""], "VSL": ["U", "Vikar Sykdom Lang", ""], "VSV": ["U", "Vikar Svangerskap", ""], "VV": ["U", "Vikar Vakant stilling", ""], "nan": ["U", "", ""]}, "357027 X Str\u00f8mme omsorgsbolig": {"A1": ["A", "", ""], "A1M": ["A", "", ""], "A2": ["A", "", ""], "A2M": ["A", "", ""], "A8": ["A", "", ""], "AAP": ["U", "AAP(vedtak NAV), l\u00f8nn STOPPET med personalmelding", ""], "AS": ["AS", "Avspasering", ""], "BPU": ["B", "Barn/Passer syk u/11 dager", ""], "D": ["D", "", ""], "D1": ["D", "", ""], "D2": ["D", "", ""], "D3": ["D", "", ""], "D4": ["D", "", ""], "D7": ["D", "", ""], "D9": ["D", "", ""], "DM": ["U", "", ""], "DM0": ["A", "", ""], "DM1": ["U", "", ""], "EM": ["EM", "Egenmelding", ""], "EMG": ["A", "XXX (fra 5/8):Egenmelding pga Graviditet (vedtak NAV)", ""], "EV": ["EV", "Ekstravakt", ""], "F1": ["F", "", ""], "F2": ["F", "", ""], "F3": ["F", "", ""], "FA": ["FK", "Forskj\u00f8vet arbeidstid", ""], "FAG": ["X", "", ""], "FAP": ["U", "AAP korttidsfrav\u00e6r (sykdom og annet)", ""], "FE": ["FE", "Ferie", ""], "FK": ["FK", "Forskj\u00f8vet arbeidstid - kort varsel", ""], "FL": ["O", "Frav\u00e6r 1", ""], "FP1": ["U", "Foreldrepermisjon 100% (vedtak NAV)", ""], "FU": ["O", "Frav\u00e6r 2", ""], "FV": ["O", "Frav\u00e6r Vakant Stilling", ""], "H3": ["F", "", ""], "IB": ["IB", "Internt bytte av vakt", ""], "KFE": ["S", "xxxKorona frav\u00e6r Egenmeldt - avvikskode 1110", ""], "KFK": ["S", "xxxKorona frav\u00e6r Karantene - avvikskode 1110", ""], "KFS": ["S", "xxxKorona frav\u00e6r Sykmeldt UNDER 17 dager - avvikskode 1997", ""], "KI": ["S", "xxxKorona  vikar ekstra/sykdom/karantene  - LTA 397. Konto 102000", ""], "OLV": ["OLV", "Oppl\u00e6ringsvakt", ""], "OT": ["OT", "Overtid", ""], "PF": ["U", "xxxPermisjon Foreldre Svangerskap", ""], "PM": ["P", "", ""], "PM1": ["U", "", ""], "PS": ["P", "Permisjon, l\u00f8nn STOPPET med personalmelding", ""], "QD": ["U", "", ""], "SMG": ["B", "XXX (fra 5/8):Sykmelding pga graviditet (vedtak NAV)", ""], "SO": ["S", "Sykmelding OVER 16 dager", ""], "SU": ["S", "Sykmelding UNDER  17 dager", ""], "VA": ["U", "Vikar Avspasering", ""], "VF": ["U", "Vikar Ferie", ""], "VK": ["U", "Vikar Kurs", ""], "VP": ["U", "Vikar Permisjon", ""], "VS": ["U", "Vikar Sykdom Kort", ""], "VSL": ["U", "Vikar Sykdom Lang", ""], "VSV": ["U", "Vikar Svangerskap", ""], "VTV": ["U", "Vikar/arb. Tillitsvalgt/Verneombud", ""], "VV": ["U", "Vikar Vakant stilling", ""], "nan": ["U", "", ""]}, "357028 x Str\u00f8mme omsorgsbolig natt": {"A2": ["A", "", ""], "A3": ["A", "", ""], "AS": ["AS", "Avspasering", ""], "DM0": ["A", "", ""], "EM": ["EM", "Egenmelding", ""], "EV": ["EV", "Ekstravakt", ""], "F1": ["F", "", ""], "F2": ["F", "", ""], "F3": ["F", "", ""], "FE": ["FE", "Ferie", ""], "FU": ["O", "Frav\u00e6r 2", ""], "IB": ["IB", "Internt bytte av vakt", ""], "KFE": ["S", "xxxKorona frav\u00e6r Egenmeldt - avvikskode 1110", ""], "KI": ["S", "xxxKorona  vikar ekstra/sykdom/karantene  - LTA 397. Konto 102000", ""], "N": ["N", "", ""], "QD": ["U", "", ""], "SF": ["F", "Seniorfri", ""], "SO": ["S", "Sykmelding OVER 16 dager", ""], "SU": ["S", "Sykmelding UNDER  17 dager", ""], "VF": ["U", "Vikar Ferie", ""], "VP": ["U", "Vikar Permisjon", ""], "VS": ["U", "Vikar Sykdom Kort", ""], "VSL": ["U", "Vikar Sykdom Lang", ""], "VV": ["U", "Vikar Vakant stilling", ""], "nan": ["U", "", ""]}, "357047 Randesund omsorgsbolig": {"A": ["A", "", ""], "A1": ["A", "", ""], "A2": ["A", "", ""], "A4": ["A", "", ""], "A5": ["A", "", ""], "AAP": ["U", "AAP(vedtak NAV), l\u00f8nn STOPPET med personalmelding", ""], "AS": ["AS", "Avspasering", ""], "AT": ["A", "", ""], "BD1": ["U", "", ""], "BPU": ["B", "Barn/Passer syk u/11 dager", ""], "D": ["D", "", ""], "D1": ["D", "", ""], "D2": ["D", "", ""], "D3": ["D", "", ""], "D4": ["D", "", ""], "D5": ["D", "", ""], "D8": ["D", "", ""], "EM": ["EM", "Egenmelding", ""], "EV": ["EV", "Ekstravakt", ""], "F1": ["F", "", ""], "F2": ["F", "", ""], "F3": ["F", "", ""], "F4": ["F", "", ""], "FA": ["FK", "Forskj\u00f8vet arbeidstid", ""], "FA1": ["FK", "", ""], "FA2": ["A", "", ""], "FAG": ["X", "", ""], "FD": ["X", "", ""], "FE": ["FE", "Ferie", ""], "FK": ["FK", "Forskj\u00f8vet arbeidstid - kort varsel", ""], "FM": ["A", "", ""], "FM1": ["A", "", ""], "FM2": ["A", "", ""], "FP1": ["U", "Foreldrepermisjon 100% (vedtak NAV)", ""], "FU": ["O", "Frav\u00e6r 2", ""], "FV": ["O", "Frav\u00e6r Vakant Stilling", ""], "H3": ["F", "", ""], "IB": ["IB", "Internt bytte av vakt", ""], "KFE": ["S", "xxxKorona frav\u00e6r Egenmeldt - avvikskode 1110", ""], "KFK": ["S", "xxxKorona frav\u00e6r Karantene - avvikskode 1110", ""], "KFS": ["S", "xxxKorona frav\u00e6r Sykmeldt UNDER 17 dager - avvikskode 1997", ""], "KI": ["S", "xxxKorona  vikar ekstra/sykdom/karantene  - LTA 397. Konto 102000", ""], "KO2": ["A", "xxxKorona OVERTID 200% (over 35,5 t/uka / 100% st.) - LTA 395", ""], "KO3": ["A", "xxxKorona OVERTID 300% (Helligdag) (fra 35,5 t/uka / 100% st.) - LTA 396", ""], "MBM": ["A", "", ""], "N": ["N", "", ""], "N1": ["N", "", ""], "N3": ["N", "", ""], "NM": ["U", "", ""], "NMD": ["A", "", ""], "OLV": ["OLV", "Oppl\u00e6ringsvakt", ""], "OT": ["OT", "Overtid", ""], "PA": ["U", "Pensjonist avl\u00f8nning", ""], "PA1": ["U", "", ""], "PA2": ["U", "", ""], "PK": ["U", "Permisjon Kurs", ""], "PM": ["P", "", ""], "PM1": ["U", "", ""], "PM2": ["U", "", ""], "PS": ["P", "Permisjon, l\u00f8nn STOPPET med personalmelding", ""], "PT": ["U", "Permisjon", ""], "PTD": ["A", "", ""], "PTV": ["P", "Permisjon TV og VO Arbeid", ""], "PV": ["P", "Permisjon Velferd", ""], "QD": ["U", "", ""], "SA1": ["A", "", ""], "SA2": ["A", "", ""], "SA3": ["A", "", ""], "SF": ["F", "Seniorfri", ""], "SM": ["U", "", ""], "SM1": ["U", "", ""], "SM2": ["U", "", ""], "SO": ["S", "Sykmelding OVER 16 dager", ""], "SU": ["S", "Sykmelding UNDER  17 dager", ""], "VA": ["U", "Vikar Avspasering", ""], "VF": ["U", "Vikar Ferie", ""], "VK": ["U", "Vikar Kurs", ""], "VP": ["U", "Vikar Permisjon", ""], "VS": ["U", "Vikar Sykdom Kort", ""], "VSL": ["U", "Vikar Sykdom Lang", ""], "VSV": ["U", "Vikar Svangerskap", ""], "VTV": ["U", "Vikar/arb. Tillitsvalgt/Verneombud", ""], "VV": ["U", "Vikar Vakant stilling", ""], "nan": ["U", "", ""]}, "357048 x Randesund omsorgsbolig natt": {"AAP": ["U", "AAP(vedtak NAV), l\u00f8nn STOPPET med personalmelding", ""], "AS": ["AS", "Avspasering", ""], "EM": ["EM", "Egenmelding", ""], "EV": ["EV", "Ekstravakt", ""], "F1": ["F", "", ""], "F2": ["F", "", ""], "F3": ["F", "", ""], "FA": ["FK", "Forskj\u00f8vet arbeidstid", ""], "FAP": ["U", "AAP korttidsfrav\u00e6r (sykdom og annet)", ""], "FD": ["X", "", ""], "FE": ["FE", "Ferie", ""], "FM": ["A", "", ""], "FU1": ["A", "", ""], "FU3": ["A", "", ""], "FU4": ["A", "", ""], "FU5": ["A", "", ""], "IB": ["IB", "Internt bytte av vakt", ""], "KFE": ["S", "xxxKorona frav\u00e6r Egenmeldt - avvikskode 1110", ""], "KFK": ["S", "xxxKorona frav\u00e6r Karantene - avvikskode 1110", ""], "KI": ["S", "xxxKorona  vikar ekstra/sykdom/karantene  - LTA 397. Konto 102000", ""], "N": ["N", "", ""], "N1": ["N", "", ""], "N3": ["N", "", ""], "NM": ["U", "", ""], "OT": ["OT", "Overtid", ""], "PM": ["P", "", ""], "PS": ["P", "Permisjon, l\u00f8nn STOPPET med personalmelding", ""], "SM": ["U", "", ""], "SO": ["S", "Sykmelding OVER 16 dager", ""], "SU": ["S", "Sykmelding UNDER  17 dager", ""], "VA": ["U", "Vikar Avspasering", ""], "VAF": ["U", "Vikar Avsp F3", ""], "VF": ["U", "Vikar Ferie", ""], "VP": ["U", "Vikar Permisjon", ""], "VS": ["U", "Vikar Sykdom Kort", ""], "VSL": ["U", "Vikar Sykdom Lang", ""], "VV": ["U", "Vikar Vakant stilling", ""], "nan": ["U", "", ""]}, "357061 x Str\u00f8mmehaven natt": {"AS": ["AS", "Avspasering", ""], "BKU": ["A", "xxxKorona Barn/Passer syk u/11 dager - avvikskode 190", ""], "BPU": ["B", "Barn/Passer syk u/11 dager", ""], "EM": ["EM", "Egenmelding", ""], "EV": ["EV", "Ekstravakt", ""], "F1": ["F", "", ""], "F1A": ["F", "", ""], "F1D": ["F", "", ""], "F2": ["F", "", ""], "F2A": ["F", "", ""], "F2D": ["F", "", ""], "F3": ["F", "", ""], "FA": ["FK", "Forskj\u00f8vet arbeidstid", ""], "FD": ["X", "", ""], "FE": ["FE", "Ferie", ""], "IB": ["IB", "Internt bytte av vakt", ""], "KFE": ["S", "xxxKorona frav\u00e6r Egenmeldt - avvikskode 1110", ""], "KFK": ["S", "xxxKorona frav\u00e6r Karantene - avvikskode 1110", ""], "KFS": ["S", "xxxKorona frav\u00e6r Sykmeldt UNDER 17 dager - avvikskode 1997", ""], "LV": ["U", "", ""], "M\u00d8": ["A", "", ""], "NF": ["U", "", ""], "NM\u00d8": ["A", "", ""], "NS": ["U", "", ""], "OLV": ["OLV", "Oppl\u00e6ringsvakt", ""], "OT": ["OT", "Overtid", ""], "OU": ["U", "Opptjening av fri", ""], "Q7": ["A", "", ""], "RM\u00d8": ["A", "", ""], "SO": ["S", "Sykmelding OVER 16 dager", ""], "SU": ["S", "Sykmelding UNDER  17 dager", ""], "VA": ["U", "Vikar Avspasering", ""], "VF": ["U", "Vikar Ferie", ""], "VP": ["U", "Vikar Permisjon", ""], "VS": ["U", "Vikar Sykdom Kort", ""], "VSL": ["U", "Vikar Sykdom Lang", ""], "VV": ["U", "Vikar Vakant stilling", ""], "nan": ["U", "", ""]}, "357062 Str\u00f8mmehaven avd": {"A1": ["A", "", ""], "A2": ["A", "", ""], "AA3": ["A", "", ""], "AD": ["U", "", ""], "ADM": ["K", "", ""], "ADP": ["U", "", ""], "AS": ["AS", "Avspasering", ""], "BKU": ["A", "xxxKorona Barn/Passer syk u/11 dager - avvikskode 190", ""], "BPU": ["B", "Barn/Passer syk u/11 dager", ""], "B\u00d8": ["A", "", ""], "D": ["D", "", ""], "D1": ["D", "", ""], "EM": ["EM", "Egenmelding", ""], "EMK": ["S", "XXX (fra 5/8): Egenmelding Kronisk Syk (vedtak NAV)", ""], "EQ": ["U", "", ""], "EV": ["EV", "Ekstravakt", ""], "F1": ["F", "", ""], "F1A": ["F", "", ""], "F1D": ["F", "", ""], "F2": ["F", "", ""], "F2A": ["F", "", ""], "F2D": ["F", "", ""], "F3": ["F", "", ""], "F5": ["F", "", ""], "FA": ["FK", "Forskj\u00f8vet arbeidstid", ""], "FA1": ["FK", "", ""], "FAP": ["U", "", ""], "FD": ["X", "", ""], "FD1": ["A", "", ""], "FD2": ["A", "", ""], "FDP": ["U", "", ""], "FE": ["FE", "Ferie", ""], "FK": ["FK", "Forskj\u00f8vet arbeidstid - kort varsel", ""], "FL": ["O", "Frav\u00e6r 1", ""], "FU": ["O", "Frav\u00e6r 2", ""], "FV": ["O", "Frav\u00e6r Vakant Stilling", ""], "GM\u00d8": ["A", "", ""], "H3": ["F", "", ""], "H3N": ["F", "", ""], "IB": ["IB", "Internt bytte av vakt", ""], "KFE": ["S", "xxxKorona frav\u00e6r Egenmeldt - avvikskode 1110", ""], "KFK": ["S", "xxxKorona frav\u00e6r Karantene - avvikskode 1110", ""], "KFS": ["S", "xxxKorona frav\u00e6r Sykmeldt UNDER 17 dager - avvikskode 1997", ""], "KI": ["S", "xxxKorona  vikar ekstra/sykdom/karantene  - LTA 397. Konto 102000", ""], "KO2": ["A", "xxxKorona OVERTID 200% (over 35,5 t/uka / 100% st.) - LTA 395", ""], "KO3": ["A", "xxxKorona OVERTID 300% (Helligdag) (fra 35,5 t/uka / 100% st.) - LTA 396", ""], "KSL": ["U", "XXX (fra 5/8):Sykmelding Kronisk (vedtak NAV)", ""], "KT": ["U", "", ""], "LV": ["U", "", ""], "MK": ["A", "", ""], "MM\u00d8": ["A", "", ""], "M\u00d8": ["A", "", ""], "NF": ["U", "", ""], "NM\u00d8": ["A", "", ""], "NS": ["U", "", ""], "OLV": ["OLV", "Oppl\u00e6ringsvakt", ""], "OT": ["OT", "Overtid", ""], "OU": ["U", "Opptjening av fri", ""], "PA": ["U", "Pensjonist avl\u00f8nning", ""], "PK": ["U", "Permisjon Kurs", ""], "PKT": ["U", "xxxKorona vikar pensjonist timel\u00f8nn(LTA 399. KOnto 102000)", ""], "PM": ["P", "Permisjon Med L\u00f8nn", ""], "PT": ["U", "Permisjon", ""], "PTV": ["P", "Permisjon TV og VO Arbeid", ""], "PV": ["P", "Permisjon Velferd", ""], "Q7": ["A", "", ""], "RA": ["U", "", ""], "RA1": ["U", "", ""], "RAP": ["U", "", ""], "RD": ["U", "", ""], "RDP": ["U", "", ""], "RH": ["U", "", ""], "RM": ["U", "", ""], "RM1": ["A", "", ""], "RMP": ["U", "", ""], "RM\u00d8": ["A", "", ""], "RTA": ["A", "", ""], "RTD": ["A", "", ""], "SA": ["U", "", ""], "SAH": ["U", "", ""], "SD": ["U", "", ""], "SDH": ["U", "", ""], "SDP": ["A", "", ""], "SF": ["F", "Seniorfri", ""], "SLA": ["A", "", ""], "SMG": ["B", "XXX (fra 5/8):Sykmelding pga graviditet (vedtak NAV)", ""], "SO": ["S", "Sykmelding OVER 16 dager", ""], "SP": ["U", "Svangerskapspenger (vedtak NAV - HUSK kopi av s\u00f8knad til l\u00f8nsavd.)", ""], "SU": ["S", "Sykmelding UNDER  17 dager", ""], "TK": ["U", "", ""], "TUR": ["A", "", ""], "U1": ["A", "", ""], "U2": ["A", "", ""], "VA": ["U", "Vikar Avspasering", ""], "VAF": ["U", "Vikar Avsp F3", ""], "VF": ["U", "Vikar Ferie", ""], "VK": ["U", "Vikar Kurs", ""], "VP": ["U", "Vikar Permisjon", ""], "VS": ["U", "Vikar Sykdom Kort", ""], "VSL": ["U", "Vikar Sykdom Lang", ""], "VTV": ["U", "Vikar/arb. Tillitsvalgt/Verneombud", ""], "VV": ["U", "Vikar Vakant stilling", ""], "nan": ["U", "", ""]}}